ekler/__init__.py
ekler/aykiri.py
ekler/bulunma.py
ekler/cogul.py
ekler/iyelik.py
ekler/vasita.py
ekler/yonelme.py
ekler-0.6.1.dist-info/LICENCE
ekler-0.6.1.dist-info/METADATA
ekler-0.6.1.dist-info/WHEEL
ekler-0.6.1.dist-info/top_level.txt
ekler-0.6.1.dist-info/RECORD
