Metadata-Version: 2.1
Name: ekler
Version: 0.6.1
Summary: Turkce kelimelerin sonuna fonetik yapilarina uygun ekleri ekleyen module.
Home-page: https://github.com/alioguzhan/ekler
Author: Ali Oguzhan Yildiz
Author-email: aoguzhanyildiz@gmail.com
License: MIT
Keywords: turkish,turkce,isim,ekler
Platform: UNKNOWN
Classifier: Development Status :: 5 - Production/Stable
Classifier: Intended Audience :: Developers
Classifier: License :: OSI Approved :: MIT License
Classifier: Operating System :: OS Independent
Classifier: Programming Language :: Python :: 3
Classifier: Topic :: Utilities
Requires-Python: >=3
